{
    "ansible_facts": {
        "ansible_net_all_ipv4_addresses": [
            "10.254.255.1",
            "10.254.255.9",
            "10.254.1.252"
        ],
        "ansible_net_all_ipv6_addresses": [],
        "ansible_net_api": "cliconf",
        "ansible_net_filesystems": [
            "flash:"
        ],
        "ansible_net_filesystems_info": {
            "flash:": {
                "spacefree_kb": 9629.0,
                "spacetotal_kb": 31752.0
            }
        },
        "ansible_net_gather_network_resources": [],
        "ansible_net_gather_subset": [
            "hardware",
            "default",
            "interfaces"
        ],
        "ansible_net_hostname": "MAN-sw2-Wolica_c3560G",
        "ansible_net_image": "flash:c3560-ipservicesk9-mz.122-55.SE8.bin",
        "ansible_net_interfaces": {
            "GigabitEthernet0/1": {
                "bandwidth": 1000000,
                "description": "**Inet dla MAN ***",
                "duplex": null,
                "ipv4": [],
                "lineprotocol": null,
                "macaddress": "0023.05e2.c201",
                "mediatype": "10/100/1000BaseTX",
                "mtu": 9000,
                "operstatus": "up",
                "type": "Gigabit Ethernet"
            },
            "GigabitEthernet0/10": {
                "bandwidth": 10000,
                "description": null,
                "duplex": null,
                "ipv4": [],
                "lineprotocol": null,
                "macaddress": "0023.05e2.c20a",
                "mediatype": "10/100/1000BaseTX",
                "mtu": 9000,
                "operstatus": "down",
                "type": "Gigabit Ethernet"
            },
            "GigabitEthernet0/11": {
                "bandwidth": 10000,
                "description": null,
                "duplex": null,
                "ipv4": [],
                "lineprotocol": null,
                "macaddress": "0023.05e2.c20b",
                "mediatype": "10/100/1000BaseTX",
                "mtu": 9000,
                "operstatus": "down",
                "type": "Gigabit Ethernet"
            },
            "GigabitEthernet0/12": {
                "bandwidth": 10000,
                "description": null,
                "duplex": null,
                "ipv4": [],
                "lineprotocol": null,
                "macaddress": "0023.05e2.c20c",
                "mediatype": "10/100/1000BaseTX",
                "mtu": 9000,
                "operstatus": "down",
                "type": "Gigabit Ethernet"
            },
            "GigabitEthernet0/13": {
                "bandwidth": 10000,
                "description": null,
                "duplex": null,
                "ipv4": [],
                "lineprotocol": null,
                "macaddress": "0023.05e2.c20d",
                "mediatype": "10/100/1000BaseTX",
                "mtu": 9000,
                "operstatus": "down",
                "type": "Gigabit Ethernet"
            },
            "GigabitEthernet0/14": {
                "bandwidth": 10000,
                "description": null,
                "duplex": null,
                "ipv4": [],
                "lineprotocol": null,
                "macaddress": "0023.05e2.c20e",
                "mediatype": "10/100/1000BaseTX",
                "mtu": 9000,
                "operstatus": "down",
                "type": "Gigabit Ethernet"
            },
            "GigabitEthernet0/15": {
                "bandwidth": 10000,
                "description": null,
                "duplex": null,
                "ipv4": [],
                "lineprotocol": null,
                "macaddress": "0023.05e2.c20f",
                "mediatype": "10/100/1000BaseTX",
                "mtu": 9000,
                "operstatus": "down",
                "type": "Gigabit Ethernet"
            },
            "GigabitEthernet0/16": {
                "bandwidth": 10000,
                "description": null,
                "duplex": null,
                "ipv4": [],
                "lineprotocol": null,
                "macaddress": "0023.05e2.c210",
                "mediatype": "10/100/1000BaseTX",
                "mtu": 9000,
                "operstatus": "down",
                "type": "Gigabit Ethernet"
            },
            "GigabitEthernet0/17": {
                "bandwidth": 10000,
                "description": null,
                "duplex": null,
                "ipv4": [],
                "lineprotocol": null,
                "macaddress": "0023.05e2.c211",
                "mediatype": "10/100/1000BaseTX",
                "mtu": 9000,
                "operstatus": "down",
                "type": "Gigabit Ethernet"
            },
            "GigabitEthernet0/18": {
                "bandwidth": 10000,
                "description": null,
                "duplex": null,
                "ipv4": [],
                "lineprotocol": null,
                "macaddress": "0023.05e2.c212",
                "mediatype": "10/100/1000BaseTX",
                "mtu": 9000,
                "operstatus": "down",
                "type": "Gigabit Ethernet"
            },
            "GigabitEthernet0/19": {
                "bandwidth": 10000,
                "description": null,
                "duplex": null,
                "ipv4": [],
                "lineprotocol": null,
                "macaddress": "0023.05e2.c213",
                "mediatype": "10/100/1000BaseTX",
                "mtu": 9000,
                "operstatus": "down",
                "type": "Gigabit Ethernet"
            },
            "GigabitEthernet0/2": {
                "bandwidth": 1000000,
                "description": "**IPVPN2 WiFi oddzialy **",
                "duplex": null,
                "ipv4": [],
                "lineprotocol": null,
                "macaddress": "0023.05e2.c202",
                "mediatype": "10/100/1000BaseTX",
                "mtu": 9000,
                "operstatus": "up",
                "type": "Gigabit Ethernet"
            },
            "GigabitEthernet0/20": {
                "bandwidth": 10000,
                "description": null,
                "duplex": null,
                "ipv4": [],
                "lineprotocol": null,
                "macaddress": "0023.05e2.c214",
                "mediatype": "10/100/1000BaseTX",
                "mtu": 9000,
                "operstatus": "down",
                "type": "Gigabit Ethernet"
            },
            "GigabitEthernet0/21": {
                "bandwidth": 10000,
                "description": null,
                "duplex": null,
                "ipv4": [],
                "lineprotocol": null,
                "macaddress": "0023.05e2.c215",
                "mediatype": "10/100/1000BaseTX",
                "mtu": 9000,
                "operstatus": "down",
                "type": "Gigabit Ethernet"
            },
            "GigabitEthernet0/22": {
                "bandwidth": 10000,
                "description": null,
                "duplex": null,
                "ipv4": [],
                "lineprotocol": null,
                "macaddress": "0023.05e2.c216",
                "mediatype": "10/100/1000BaseTX",
                "mtu": 9000,
                "operstatus": "down",
                "type": "Gigabit Ethernet"
            },
            "GigabitEthernet0/23": {
                "bandwidth": 10000,
                "description": null,
                "duplex": null,
                "ipv4": [],
                "lineprotocol": null,
                "macaddress": "0023.05e2.c217",
                "mediatype": "10/100/1000BaseTX",
                "mtu": 9000,
                "operstatus": "down",
                "type": "Gigabit Ethernet"
            },
            "GigabitEthernet0/24": {
                "bandwidth": 10000,
                "description": null,
                "duplex": null,
                "ipv4": [],
                "lineprotocol": null,
                "macaddress": "0023.05e2.c218",
                "mediatype": "10/100/1000BaseTX",
                "mtu": 9000,
                "operstatus": "down",
                "type": "Gigabit Ethernet"
            },
            "GigabitEthernet0/25": {
                "bandwidth": 10000,
                "description": null,
                "duplex": null,
                "ipv4": [],
                "lineprotocol": null,
                "macaddress": "0023.05e2.c219",
                "mediatype": "10/100/1000BaseTX",
                "mtu": 9000,
                "operstatus": "down",
                "type": "Gigabit Ethernet"
            },
            "GigabitEthernet0/26": {
                "bandwidth": 10000,
                "description": null,
                "duplex": null,
                "ipv4": [],
                "lineprotocol": null,
                "macaddress": "0023.05e2.c21a",
                "mediatype": "10/100/1000BaseTX",
                "mtu": 9000,
                "operstatus": "down",
                "type": "Gigabit Ethernet"
            },
            "GigabitEthernet0/27": {
                "bandwidth": 10000,
                "description": null,
                "duplex": null,
                "ipv4": [],
                "lineprotocol": null,
                "macaddress": "0023.05e2.c21b",
                "mediatype": "10/100/1000BaseTX",
                "mtu": 9000,
                "operstatus": "down",
                "type": "Gigabit Ethernet"
            },
            "GigabitEthernet0/28": {
                "bandwidth": 10000,
                "description": null,
                "duplex": null,
                "ipv4": [],
                "lineprotocol": null,
                "macaddress": "0023.05e2.c21c",
                "mediatype": "10/100/1000BaseTX",
                "mtu": 9000,
                "operstatus": "down",
                "type": "Gigabit Ethernet"
            },
            "GigabitEthernet0/29": {
                "bandwidth": 10000,
                "description": null,
                "duplex": null,
                "ipv4": [],
                "lineprotocol": null,
                "macaddress": "0023.05e2.c21d",
                "mediatype": "10/100/1000BaseTX",
                "mtu": 9000,
                "operstatus": "down",
                "type": "Gigabit Ethernet"
            },
            "GigabitEthernet0/3": {
                "bandwidth": 10000,
                "description": null,
                "duplex": null,
                "ipv4": [],
                "lineprotocol": null,
                "macaddress": "0023.05e2.c203",
                "mediatype": "10/100/1000BaseTX",
                "mtu": 9000,
                "operstatus": "down",
                "type": "Gigabit Ethernet"
            },
            "GigabitEthernet0/30": {
                "bandwidth": 10000,
                "description": null,
                "duplex": null,
                "ipv4": [],
                "lineprotocol": null,
                "macaddress": "0023.05e2.c21e",
                "mediatype": "10/100/1000BaseTX",
                "mtu": 9000,
                "operstatus": "down",
                "type": "Gigabit Ethernet"
            },
            "GigabitEthernet0/31": {
                "bandwidth": 10000,
                "description": null,
                "duplex": null,
                "ipv4": [],
                "lineprotocol": null,
                "macaddress": "0023.05e2.c21f",
                "mediatype": "10/100/1000BaseTX",
                "mtu": 9000,
                "operstatus": "down",
                "type": "Gigabit Ethernet"
            },
            "GigabitEthernet0/32": {
                "bandwidth": 10000,
                "description": null,
                "duplex": null,
                "ipv4": [],
                "lineprotocol": null,
                "macaddress": "0023.05e2.c220",
                "mediatype": "10/100/1000BaseTX",
                "mtu": 9000,
                "operstatus": "down",
                "type": "Gigabit Ethernet"
            },
            "GigabitEthernet0/33": {
                "bandwidth": 10000,
                "description": null,
                "duplex": null,
                "ipv4": [],
                "lineprotocol": null,
                "macaddress": "0023.05e2.c221",
                "mediatype": "10/100/1000BaseTX",
                "mtu": 9000,
                "operstatus": "down",
                "type": "Gigabit Ethernet"
            },
            "GigabitEthernet0/34": {
                "bandwidth": 10000,
                "description": null,
                "duplex": null,
                "ipv4": [],
                "lineprotocol": null,
                "macaddress": "0023.05e2.c222",
                "mediatype": "10/100/1000BaseTX",
                "mtu": 9000,
                "operstatus": "down",
                "type": "Gigabit Ethernet"
            },
            "GigabitEthernet0/35": {
                "bandwidth": 10000,
                "description": null,
                "duplex": null,
                "ipv4": [],
                "lineprotocol": null,
                "macaddress": "0023.05e2.c223",
                "mediatype": "10/100/1000BaseTX",
                "mtu": 9000,
                "operstatus": "down",
                "type": "Gigabit Ethernet"
            },
            "GigabitEthernet0/36": {
                "bandwidth": 10000,
                "description": null,
                "duplex": null,
                "ipv4": [],
                "lineprotocol": null,
                "macaddress": "0023.05e2.c224",
                "mediatype": "10/100/1000BaseTX",
                "mtu": 9000,
                "operstatus": "down",
                "type": "Gigabit Ethernet"
            },
            "GigabitEthernet0/37": {
                "bandwidth": 10000,
                "description": null,
                "duplex": null,
                "ipv4": [],
                "lineprotocol": null,
                "macaddress": "0023.05e2.c225",
                "mediatype": "10/100/1000BaseTX",
                "mtu": 9000,
                "operstatus": "down",
                "type": "Gigabit Ethernet"
            },
            "GigabitEthernet0/38": {
                "bandwidth": 10000,
                "description": null,
                "duplex": null,
                "ipv4": [],
                "lineprotocol": null,
                "macaddress": "0023.05e2.c226",
                "mediatype": "10/100/1000BaseTX",
                "mtu": 9000,
                "operstatus": "down",
                "type": "Gigabit Ethernet"
            },
            "GigabitEthernet0/39": {
                "bandwidth": 10000,
                "description": null,
                "duplex": null,
                "ipv4": [],
                "lineprotocol": null,
                "macaddress": "0023.05e2.c227",
                "mediatype": "10/100/1000BaseTX",
                "mtu": 9000,
                "operstatus": "down",
                "type": "Gigabit Ethernet"
            },
            "GigabitEthernet0/4": {
                "bandwidth": 10000,
                "description": null,
                "duplex": null,
                "ipv4": [],
                "lineprotocol": null,
                "macaddress": "0023.05e2.c204",
                "mediatype": "10/100/1000BaseTX",
                "mtu": 9000,
                "operstatus": "down",
                "type": "Gigabit Ethernet"
            },
            "GigabitEthernet0/40": {
                "bandwidth": 10000,
                "description": null,
                "duplex": null,
                "ipv4": [],
                "lineprotocol": null,
                "macaddress": "0023.05e2.c228",
                "mediatype": "10/100/1000BaseTX",
                "mtu": 9000,
                "operstatus": "down",
                "type": "Gigabit Ethernet"
            },
            "GigabitEthernet0/41": {
                "bandwidth": 10000,
                "description": null,
                "duplex": null,
                "ipv4": [],
                "lineprotocol": null,
                "macaddress": "0023.05e2.c229",
                "mediatype": "10/100/1000BaseTX",
                "mtu": 9000,
                "operstatus": "down",
                "type": "Gigabit Ethernet"
            },
            "GigabitEthernet0/42": {
                "bandwidth": 10000,
                "description": null,
                "duplex": null,
                "ipv4": [],
                "lineprotocol": null,
                "macaddress": "0023.05e2.c22a",
                "mediatype": "10/100/1000BaseTX",
                "mtu": 9000,
                "operstatus": "down",
                "type": "Gigabit Ethernet"
            },
            "GigabitEthernet0/43": {
                "bandwidth": 10000,
                "description": null,
                "duplex": null,
                "ipv4": [],
                "lineprotocol": null,
                "macaddress": "0023.05e2.c22b",
                "mediatype": "10/100/1000BaseTX",
                "mtu": 9000,
                "operstatus": "down",
                "type": "Gigabit Ethernet"
            },
            "GigabitEthernet0/44": {
                "bandwidth": 10000,
                "description": null,
                "duplex": null,
                "ipv4": [],
                "lineprotocol": null,
                "macaddress": "0023.05e2.c22c",
                "mediatype": "10/100/1000BaseTX",
                "mtu": 9000,
                "operstatus": "down",
                "type": "Gigabit Ethernet"
            },
            "GigabitEthernet0/45": {
                "bandwidth": 10000,
                "description": "**test uplink ***",
                "duplex": null,
                "ipv4": [],
                "lineprotocol": null,
                "macaddress": "0023.05e2.c22d",
                "mediatype": "10/100/1000BaseTX",
                "mtu": 9000,
                "operstatus": "down",
                "type": "Gigabit Ethernet"
            },
            "GigabitEthernet0/46": {
                "bandwidth": 10000,
                "description": "**do upgr softu w biurze ***",
                "duplex": null,
                "ipv4": [],
                "lineprotocol": null,
                "macaddress": "0023.05e2.c22e",
                "mediatype": "10/100/1000BaseTX",
                "mtu": 9000,
                "operstatus": "down",
                "type": "Gigabit Ethernet"
            },
            "GigabitEthernet0/47": {
                "bandwidth": 1000000,
                "description": "**zapetlony do Gi0/48, c-vlan-y klienta**",
                "duplex": null,
                "ipv4": [],
                "lineprotocol": null,
                "macaddress": "0023.05e2.c22f",
                "mediatype": "10/100/1000BaseTX",
                "mtu": 9000,
                "operstatus": "up",
                "type": "Gigabit Ethernet"
            },
            "GigabitEthernet0/48": {
                "bandwidth": 1000000,
                "description": "**encaps do QinQ dla portu gi0/47 **",
                "duplex": null,
                "ipv4": [],
                "lineprotocol": null,
                "macaddress": "0023.05e2.c230",
                "mediatype": "10/100/1000BaseTX",
                "mtu": 9000,
                "operstatus": "up",
                "type": "Gigabit Ethernet"
            },
            "GigabitEthernet0/49": {
                "bandwidth": 10000,
                "description": null,
                "duplex": null,
                "ipv4": [],
                "lineprotocol": null,
                "macaddress": "0023.05e2.c231",
                "mediatype": "Not Present",
                "mtu": 9000,
                "operstatus": "down",
                "type": "Gigabit Ethernet"
            },
            "GigabitEthernet0/5": {
                "bandwidth": 10000,
                "description": null,
                "duplex": null,
                "ipv4": [],
                "lineprotocol": null,
                "macaddress": "0023.05e2.c205",
                "mediatype": "10/100/1000BaseTX",
                "mtu": 9000,
                "operstatus": "down",
                "type": "Gigabit Ethernet"
            },
            "GigabitEthernet0/50": {
                "bandwidth": 10000,
                "description": "***Uplink do FO VirtuaOp-> LINX **",
                "duplex": null,
                "ipv4": [],
                "lineprotocol": null,
                "macaddress": "0023.05e2.c232",
                "mediatype": "Not Present",
                "mtu": 9000,
                "operstatus": "down",
                "type": "Gigabit Ethernet"
            },
            "GigabitEthernet0/51": {
                "bandwidth": 10000,
                "description": null,
                "duplex": null,
                "ipv4": [],
                "lineprotocol": null,
                "macaddress": "0023.05e2.c233",
                "mediatype": "Not Present",
                "mtu": 9000,
                "operstatus": "down",
                "type": "Gigabit Ethernet"
            },
            "GigabitEthernet0/52": {
                "bandwidth": 1000000,
                "description": "***Uplink do FO VirtuaOp-> LINX **",
                "duplex": null,
                "ipv4": [],
                "lineprotocol": null,
                "macaddress": "0023.05e2.c234",
                "mediatype": "1000BaseBX10-U SFP",
                "mtu": 9000,
                "operstatus": "up",
                "type": "Gigabit Ethernet"
            },
            "GigabitEthernet0/6": {
                "bandwidth": 10000,
                "description": null,
                "duplex": null,
                "ipv4": [],
                "lineprotocol": null,
                "macaddress": "0023.05e2.c206",
                "mediatype": "10/100/1000BaseTX",
                "mtu": 9000,
                "operstatus": "down",
                "type": "Gigabit Ethernet"
            },
            "GigabitEthernet0/7": {
                "bandwidth": 10000,
                "description": null,
                "duplex": null,
                "ipv4": [],
                "lineprotocol": null,
                "macaddress": "0023.05e2.c207",
                "mediatype": "10/100/1000BaseTX",
                "mtu": 9000,
                "operstatus": "down",
                "type": "Gigabit Ethernet"
            },
            "GigabitEthernet0/8": {
                "bandwidth": 10000,
                "description": null,
                "duplex": null,
                "ipv4": [],
                "lineprotocol": null,
                "macaddress": "0023.05e2.c208",
                "mediatype": "10/100/1000BaseTX",
                "mtu": 9000,
                "operstatus": "down",
                "type": "Gigabit Ethernet"
            },
            "GigabitEthernet0/9": {
                "bandwidth": 10000,
                "description": null,
                "duplex": null,
                "ipv4": [],
                "lineprotocol": null,
                "macaddress": "0023.05e2.c209",
                "mediatype": "10/100/1000BaseTX",
                "mtu": 9000,
                "operstatus": "down",
                "type": "Gigabit Ethernet"
            },
            "Vlan1": {
                "bandwidth": 1000000,
                "description": null,
                "duplex": null,
                "ipv4": [],
                "lineprotocol": "down",
                "macaddress": "0023.05e2.c240",
                "mediatype": null,
                "mtu": 1998,
                "operstatus": "administratively down",
                "type": "EtherSVI"
            },
            "Vlan2291": {
                "bandwidth": 1000000,
                "description": "**int ip ew. do uruchomienia qinq ***",
                "duplex": null,
                "ipv4": [
                    {
                        "address": "10.254.255.9",
                        "subnet": "29"
                    }
                ],
                "lineprotocol": "up",
                "macaddress": "0023.05e2.c243",
                "mediatype": null,
                "mtu": 1998,
                "operstatus": "up",
                "type": "EtherSVI"
            },
            "Vlan8": {
                "bandwidth": 1000000,
                "description": "**MGT **",
                "duplex": null,
                "ipv4": [
                    {
                        "address": "10.254.255.1",
                        "subnet": "29"
                    }
                ],
                "lineprotocol": "up",
                "macaddress": "0023.05e2.c241",
                "mediatype": null,
                "mtu": 1998,
                "operstatus": "up",
                "type": "EtherSVI"
            },
            "Vlan9": {
                "bandwidth": 1000000,
                "description": null,
                "duplex": null,
                "ipv4": [
                    {
                        "address": "10.254.1.252",
                        "subnet": "24"
                    }
                ],
                "lineprotocol": "down",
                "macaddress": "0023.05e2.c242",
                "mediatype": null,
                "mtu": 1998,
                "operstatus": "up",
                "type": "EtherSVI"
            }
        },
        "ansible_net_iostype": "IOS",
        "ansible_net_memfree_mb": 41133.609375,
        "ansible_net_memtotal_mb": 73881.4765625,
        "ansible_net_model": "WS-C3560G-48TS",
        "ansible_net_neighbors": {},
        "ansible_net_python_version": "2.7.17",
        "ansible_net_serialnum": "FOC1235Y4YP",
        "ansible_net_stacked_models": [
            "WS-C3560G-48TS-S"
        ],
        "ansible_net_stacked_serialnums": [
            "FOC1235Y4YP"
        ],
        "ansible_net_system": "ios",
        "ansible_net_version": "12.2(55)SE8",
        "ansible_network_resources": {},
        "discovered_interpreter_python": "/usr/bin/python"
    },
    "changed": false,
    "deprecations": [
        {
            "msg": "Distribution Ubuntu 18.04 on host MAN-SW2-c2650G_Wolica should use /usr/bin/python3, but is using /usr/bin/python for backward compatibility with prior Ansible releases. A future Ansible release will default to using the discovered platform python for this host. See https://docs.ansible.com/ansible/2.10/reference_appendices/interpreter_discovery.html for more information",
            "version": "2.12"
        }
    ],
    "failed": false
}